openpe/__init__.py
openpe/categories.py
openpe/dataset.py
openpe/errors.py
openpe/module.py
openpe/utils.py
openpe/webscraper.py
openpe-0.3.6.dist-info/LICENSE
openpe-0.3.6.dist-info/METADATA
openpe-0.3.6.dist-info/WHEEL
openpe-0.3.6.dist-info/top_level.txt
openpe-0.3.6.dist-info/RECORD
