Metadata-Version: 2.2
Name: openpe
Version: 0.3.6
Summary: Open Python Package for simple access to Peruvian Open Data
Author-email: Ivan <your.email@example.com>
License: MIT
Requires-Python: >=3.7
License-File: LICENSE
Requires-Dist: requests
Requires-Dist: beautifulsoup4
Requires-Dist: pandas
Requires-Dist: tqdm
Requires-Dist: openpyxl
